{
  "indices": [
    {
      "ticker": "^GSPC",
      "label": "S&P 500",
      "url": "https://finance.yahoo.com/quote/^GSPC",
      "price": 6582.68994140625,
      "price_fmt": "6,582.69",
      "change": 7.3701171875,
      "change_fmt": "7.3701",
      "change_pct": 0.0011208758485562616,
      "change_pct_fmt": "+0.11%",
      "change_arrow": "▲",
      "css": "up",
      "history": [
        "6,368.85",
        "6,343.72",
        "6,528.52",
        "6,575.32",
        "6,582.69"
      ],
      "history_dates": [
        "03/27",
        "03/30",
        "03/31",
        "04/01",
        "04/02"
      ],
      "change_5d": 0.033575895251278326,
      "change_5d_fmt": "+3.36%",
      "css5d": "up",
      "as_of": "04/03 05:00",
      "market_name": "NYSE/NASDAQ",
      "market_open": false,
      "name": "S&P 500",
      "news_titles": [],
      "analysis": "市场呈现高位窄幅震荡，标普微涨，投资者在财报季前保持谨慎乐观，资金流入稳健。\n核心蓝筹股支撑力较强，市场情绪整体偏向稳健增长。",
      "outlook": "bullish",
      "outlook_css": "bullish"
    },
    {
      "ticker": "^IXIC",
      "label": "NASDAQ",
      "url": "https://finance.yahoo.com/quote/^IXIC",
      "price": 21879.1796875,
      "price_fmt": "21,879",
      "change": 38.23046875,
      "change_fmt": "38.230",
      "change_pct": 0.001750403261648534,
      "change_pct_fmt": "+0.18%",
      "change_arrow": "▲",
      "css": "up",
      "history": [
        "20,948",
        "20,795",
        "21,591",
        "21,841",
        "21,879"
      ],
      "history_dates": [
        "03/27",
        "03/30",
        "03/31",
        "04/01",
        "04/02"
      ],
      "change_5d": 0.044434043537120674,
      "change_5d_fmt": "+4.44%",
      "css5d": "up",
      "as_of": "04/03 05:00",
      "market_name": "NYSE/NASDAQ",
      "market_open": false,
      "name": "NASDAQ",
      "news_titles": [],
      "analysis": "纳指在科技股领涨下微幅收高，成长性资产依旧受青睐，反映出市场对AI相关领域的信心。\n大型科技股表现韧性，为指数进一步冲高提供动力。",
      "outlook": "bullish",
      "outlook_css": "bullish"
    },
    {
      "ticker": "^DJI",
      "label": "Dow Jones",
      "url": "https://finance.yahoo.com/quote/^DJI",
      "price": 46504.671875,
      "price_fmt": "46,505",
      "change": -61.06640625,
      "change_fmt": "61.066",
      "change_pct": -0.001311402084536235,
      "change_pct_fmt": "-0.13%",
      "change_arrow": "▼",
      "css": "down",
      "history": [
        "45,167",
        "45,216",
        "46,342",
        "46,566",
        "46,505"
      ],
      "history_dates": [
        "03/27",
        "03/30",
        "03/31",
        "04/01",
        "04/02"
      ],
      "change_5d": 0.029624325198526983,
      "change_5d_fmt": "+2.96%",
      "css5d": "up",
      "as_of": "04/03 05:00",
      "market_name": "NYSE/NASDAQ",
      "market_open": false,
      "name": "Dow Jones",
      "news_titles": [],
      "analysis": "道指因权重股整理微幅收跌，市场进入横盘整理期，波动率处于较低水平。\n指数处于历史高位，短期面临获利回吐带来的压力。",
      "outlook": "neutral",
      "outlook_css": "neutral"
    },
    {
      "ticker": "^N225",
      "label": "Nikkei 225",
      "url": "https://finance.yahoo.com/quote/^N225",
      "price": 53770.3984375,
      "price_fmt": "53,770",
      "change": 646.91015625,
      "change_fmt": "646.91",
      "change_pct": 0.012177478873847366,
      "change_pct_fmt": "+1.22%",
      "change_arrow": "▲",
      "css": "up",
      "history": [
        "51,064",
        "53,740",
        "52,463",
        "53,123",
        "53,770"
      ],
      "history_dates": [
        "03/31",
        "04/01",
        "04/02",
        "04/03",
        "04/06"
      ],
      "change_5d": 0.05300592580715638,
      "change_5d_fmt": "+5.30%",
      "css5d": "up",
      "as_of": "04/06 13:48",
      "market_name": "TSE",
      "market_open": true,
      "name": "Nikkei 225",
      "news_titles": [],
      "analysis": "昨日强势反弹，日经225表现强劲，市场情绪回暖，带动今日开盘预期乐观。\n上升趋势明确，且受外部科技股上涨情绪传导带动。",
      "outlook": "bullish",
      "outlook_css": "bullish"
    },
    {
      "ticker": "^HSI",
      "label": "Hang Seng",
      "url": "https://finance.yahoo.com/quote/^HSI",
      "price": 25116.529296875,
      "price_fmt": "25,117",
      "change": -177.5,
      "change_fmt": "177.50",
      "change_pct": -0.0070174663718733645,
      "change_pct_fmt": "-0.70%",
      "change_arrow": "▼",
      "css": "down",
      "history": [
        "24,952",
        "24,751",
        "24,788",
        "25,294",
        "25,117"
      ],
      "history_dates": [
        "03/27",
        "03/30",
        "03/31",
        "04/01",
        "04/02"
      ],
      "change_5d": 0.006598638332233691,
      "change_5d_fmt": "+0.66%",
      "css5d": "up",
      "as_of": "04/02 17:00",
      "market_name": "HKEX/SGX",
      "market_open": false,
      "name": "Hang Seng",
      "news_titles": [],
      "analysis": "受区域流动性影响表现疲软，市场情绪低迷，短期走势仍受制于资金流出压力。\n资金缺乏明显的配置动能，短期难以扭转颓势。",
      "outlook": "bearish",
      "outlook_css": "bearish"
    }
  ],
  "commodities": [
    {
      "ticker": "GC=F",
      "label": "Gold",
      "url": "https://finance.yahoo.com/quote/GC=F",
      "price": 4676.5,
      "price_fmt": "4,676.50",
      "change": 25.0,
      "change_fmt": "25.000",
      "change_pct": 0.005374610340750295,
      "change_pct_fmt": "+0.54%",
      "change_arrow": "▲",
      "css": "up",
      "history": [
        "4,526.00",
        "4,647.60",
        "4,783.20",
        "4,651.50",
        "4,676.50"
      ],
      "history_dates": [
        "03/30",
        "03/31",
        "04/01",
        "04/02",
        "04/06"
      ],
      "change_5d": 0.03325231992929739,
      "change_5d_fmt": "+3.33%",
      "css5d": "up",
      "as_of": "04/06 13:48",
      "market_name": "NYSE/NASDAQ",
      "market_open": false,
      "name": "Gold",
      "news_titles": [],
      "analysis": "黄金价格受避险需求支撑持续走高，反映出宏观经济不确定性下的资产防御属性。\n全球宏观避险需求维持高位，金价具备向上突破动能。",
      "outlook": "bullish",
      "outlook_css": "bullish"
    },
    {
      "ticker": "SI=F",
      "label": "Silver",
      "url": "https://finance.yahoo.com/quote/SI=F",
      "price": 72.36499786376953,
      "price_fmt": "72.365",
      "change": -0.37000274658203125,
      "change_fmt": "0.3700",
      "change_pct": -0.005086997229355531,
      "change_pct_fmt": "-0.51%",
      "change_arrow": "▼",
      "css": "down",
      "history": [
        "70.324",
        "74.690",
        "75.867",
        "72.735",
        "72.365"
      ],
      "history_dates": [
        "03/30",
        "03/31",
        "04/01",
        "04/02",
        "04/06"
      ],
      "change_5d": 0.029022814954195314,
      "change_5d_fmt": "+2.90%",
      "css5d": "up",
      "as_of": "04/06 13:48",
      "market_name": "NYSE/NASDAQ",
      "market_open": false,
      "name": "Silver",
      "news_titles": [],
      "analysis": "白银走势与黄金出现背离，工业属性拖累表现，市场等待更明确的宏观信号。\n兼具避险与工业属性，短期面临多空拉锯。",
      "outlook": "neutral",
      "outlook_css": "neutral"
    },
    {
      "ticker": "CL=F",
      "label": "WTI Oil",
      "url": "https://finance.yahoo.com/quote/CL=F",
      "price": 111.1500015258789,
      "price_fmt": "111.15",
      "change": -0.3899993896484375,
      "change_fmt": "0.3900",
      "change_pct": -0.0034964979957620404,
      "change_pct_fmt": "-0.35%",
      "change_arrow": "▼",
      "css": "down",
      "history": [
        "102.88",
        "101.38",
        "100.12",
        "111.54",
        "111.15"
      ],
      "history_dates": [
        "03/30",
        "03/31",
        "04/01",
        "04/02",
        "04/06"
      ],
      "change_5d": 0.08038495813807173,
      "change_5d_fmt": "+8.04%",
      "css5d": "up",
      "as_of": "04/06 13:48",
      "market_name": "NYSE/NASDAQ",
      "market_open": false,
      "name": "WTI Oil",
      "news_titles": [],
      "analysis": "WTI原油微跌，主要受供需逻辑反复及市场对未来经济增长担忧影响。\n原油价格波动受宏观预期干扰，处于关键支撑位震荡。",
      "outlook": "neutral",
      "outlook_css": "neutral"
    },
    {
      "ticker": "BZ=F",
      "label": "Brent Oil",
      "url": "https://finance.yahoo.com/quote/BZ=F",
      "price": 109.66000366210938,
      "price_fmt": "109.66",
      "change": 0.6300048828125,
      "change_fmt": "0.6300",
      "change_pct": 0.005778271025094502,
      "change_pct_fmt": "+0.58%",
      "change_arrow": "▲",
      "css": "up",
      "history": [
        "112.78",
        "118.35",
        "101.16",
        "109.03",
        "109.66"
      ],
      "history_dates": [
        "03/30",
        "03/31",
        "04/01",
        "04/02",
        "04/06"
      ],
      "change_5d": -0.027664436522056784,
      "change_5d_fmt": "-2.77%",
      "css5d": "down",
      "as_of": "04/06 13:48",
      "market_name": "NYSE/NASDAQ",
      "market_open": false,
      "name": "Brent Oil",
      "news_titles": [],
      "analysis": "布伦特原油微涨，与WTI产生背离，受地缘政治风险溢价及供应端因素支撑。\n供应端紧平衡预期为油价提供下方支撑。",
      "outlook": "bullish",
      "outlook_css": "bullish"
    }
  ],
  "fx": [
    {
      "ticker": "USDJPY=X",
      "label": "USD/JPY",
      "url": "https://finance.yahoo.com/quote/USDJPY=X",
      "price": 159.5540008544922,
      "price_fmt": "159.55",
      "change": 0.0630035400390625,
      "change_fmt": "0.0630",
      "change_pct": 0.0003950288172996025,
      "change_pct_fmt": "+0.04%",
      "change_arrow": "▲",
      "css": "up",
      "history": [
        "159.84",
        "158.58",
        "158.69",
        "159.49",
        "159.55"
      ],
      "history_dates": [
        "03/31",
        "04/01",
        "04/02",
        "04/03",
        "04/06"
      ],
      "change_5d": -0.0017955503114934694,
      "change_5d_fmt": "-0.18%",
      "css5d": "down",
      "as_of": "04/06 13:48",
      "market_name": "XETRA",
      "market_open": false,
      "name": "USD/JPY",
      "news_titles": [],
      "analysis": "日元维持弱势震荡，汇率在159.5附近波动，市场关注日本央行后续政策动向。\n美日利差依旧明显，日元缺乏大幅回升的驱动力。",
      "outlook": "bearish",
      "outlook_css": "bearish"
    },
    {
      "ticker": "JPYCNY=X",
      "label": "JPY/CNY",
      "url": "https://finance.yahoo.com/quote/JPYCNY=X",
      "price": 0.04307999834418297,
      "price_fmt": "0.0431",
      "change": -8.80025327205658e-05,
      "change_fmt": "0.0001",
      "change_pct": -0.002038605701744469,
      "change_pct_fmt": "-0.20%",
      "change_arrow": "▼",
      "css": "down",
      "history": [
        "0.0432",
        "0.0435",
        "0.0433",
        "0.0432",
        "0.0431"
      ],
      "history_dates": [
        "03/31",
        "04/01",
        "04/02",
        "04/03",
        "04/06"
      ],
      "change_5d": -0.0036773014214585295,
      "change_5d_fmt": "-0.37%",
      "css5d": "down",
      "as_of": "04/06 13:48",
      "market_name": "XETRA",
      "market_open": false,
      "name": "JPY/CNY",
      "news_titles": [],
      "analysis": "日元兑人民币小幅下跌，反映出区域货币套利交易的持续影响。\n资金面偏向弱势日元，汇率持续面临贬值压力。",
      "outlook": "bearish",
      "outlook_css": "bearish"
    },
    {
      "ticker": "EURJPY=X",
      "label": "EUR/JPY",
      "url": "https://finance.yahoo.com/quote/EURJPY=X",
      "price": 183.84300231933594,
      "price_fmt": "183.84",
      "change": -0.2129974365234375,
      "change_fmt": "0.2130",
      "change_pct": -0.0011572425609921297,
      "change_pct_fmt": "-0.12%",
      "change_arrow": "▼",
      "css": "down",
      "history": [
        "183.12",
        "183.48",
        "183.90",
        "184.06",
        "183.84"
      ],
      "history_dates": [
        "03/31",
        "04/01",
        "04/02",
        "04/03",
        "04/06"
      ],
      "change_5d": 0.003931790197755232,
      "change_5d_fmt": "+0.39%",
      "css5d": "up",
      "as_of": "04/06 13:48",
      "market_name": "XETRA",
      "market_open": false,
      "name": "EUR/JPY",
      "news_titles": [],
      "analysis": "欧元兑日元微幅走弱，汇率在高位盘整，反映欧元区经济预期与日元利差的综合影响。\n双方货币均缺乏单边驱动力，预计维持区间波动。",
      "outlook": "neutral",
      "outlook_css": "neutral"
    }
  ],
  "hist_dates": [
    "03/27",
    "03/30",
    "03/31",
    "04/01",
    "04/02"
  ],
  "watchlist": [
    {
      "ticker": "IAU",
      "label": "iShares Gold Trust",
      "url": "https://finance.yahoo.com/quote/IAU",
      "price": 87.94000244140625,
      "price_fmt": "87.940",
      "change": -1.7399978637695312,
      "change_fmt": "1.7400",
      "change_pct": -0.019402295471101925,
      "change_pct_fmt": "-1.94%",
      "change_arrow": "▼",
      "css": "down",
      "history": [
        "84.950",
        "84.930",
        "88.160",
        "89.680",
        "87.940"
      ],
      "history_dates": [
        "03/27",
        "03/30",
        "03/31",
        "04/01",
        "04/02"
      ],
      "change_5d": 0.0351972407366394,
      "change_5d_fmt": "+3.52%",
      "css5d": "up",
      "as_of": "04/03 05:00",
      "market_name": "NYSE/NASDAQ",
      "market_open": false,
      "name": "iShares Gold Trust",
      "news_titles": [],
      "analysis": "IAU回撤明显，与现货黄金走势背离，短期存在机构调仓或流动性回流影响。\n基金折溢价调整，长期看好但短期有波动风险。",
      "outlook": "neutral",
      "outlook_css": "neutral"
    },
    {
      "ticker": "NEM",
      "label": "Newmont Corporation",
      "url": "https://finance.yahoo.com/quote/NEM",
      "price": 114.05000305175781,
      "price_fmt": "114.05",
      "change": 0.26000213623046875,
      "change_fmt": "0.2600",
      "change_pct": 0.0022849295556600165,
      "change_pct_fmt": "+0.23%",
      "change_arrow": "▲",
      "css": "up",
      "history": [
        "102.10",
        "103.12",
        "108.25",
        "113.79",
        "114.05"
      ],
      "history_dates": [
        "03/27",
        "03/30",
        "03/31",
        "04/01",
        "04/02"
      ],
      "change_5d": 0.11704216215699202,
      "change_5d_fmt": "+11.70%",
      "css5d": "up",
      "as_of": "04/03 05:00",
      "market_name": "NYSE/NASDAQ",
      "market_open": false,
      "name": "Newmont Corporation",
      "news_titles": [],
      "analysis": "纽蒙特矿业股价微涨，跟随黄金价格趋势，作为金矿股具备防御性价值。\n金价上涨带动利润预期改善，基本面稳健。",
      "outlook": "bullish",
      "outlook_css": "bullish"
    },
    {
      "ticker": "NVDA",
      "label": "NVIDIA",
      "url": "https://finance.yahoo.com/quote/NVDA",
      "price": 177.38999938964844,
      "price_fmt": "177.39",
      "change": 1.6399993896484375,
      "change_fmt": "1.6400",
      "change_pct": 0.009331433227018137,
      "change_pct_fmt": "+0.93%",
      "change_arrow": "▲",
      "css": "up",
      "history": [
        "167.52",
        "165.17",
        "174.40",
        "175.75",
        "177.39"
      ],
      "history_dates": [
        "03/27",
        "03/30",
        "03/31",
        "04/01",
        "04/02"
      ],
      "change_5d": 0.058918307458580066,
      "change_5d_fmt": "+5.89%",
      "css5d": "up",
      "as_of": "04/03 05:00",
      "market_name": "NYSE/NASDAQ",
      "market_open": false,
      "name": "NVIDIA",
      "news_titles": [],
      "analysis": "英伟达稳健上涨，AI算力需求持续，带动科技板块投资情绪重回高点。\n行业龙头地位不可动摇，增长前景依然广阔。",
      "outlook": "bullish",
      "outlook_css": "bullish"
    },
    {
      "ticker": "TSM",
      "label": "Taiwan Semiconductor",
      "url": "https://finance.yahoo.com/quote/TSM",
      "price": 339.0400085449219,
      "price_fmt": "339.04",
      "change": -2.449981689453125,
      "change_fmt": "2.4500",
      "change_pct": -0.0071743880040865265,
      "change_pct_fmt": "-0.72%",
      "change_arrow": "▼",
      "css": "down",
      "history": [
        "326.74",
        "316.50",
        "337.95",
        "341.49",
        "339.04"
      ],
      "history_dates": [
        "03/27",
        "03/30",
        "03/31",
        "04/01",
        "04/02"
      ],
      "change_5d": 0.03764466755882531,
      "change_5d_fmt": "+3.76%",
      "css5d": "up",
      "as_of": "04/03 05:00",
      "market_name": "NYSE/NASDAQ",
      "market_open": false,
      "name": "Taiwan Semiconductor",
      "news_titles": [],
      "analysis": "台积电小幅收跌，主要受半导体板块获利了结影响，估值处于修正阶段。\n产业需求强劲但股价短期涨幅过大，存在技术性调整压力。",
      "outlook": "neutral",
      "outlook_css": "neutral"
    },
    {
      "ticker": "BRK-B",
      "label": "Berkshire Hathaway B",
      "url": "https://finance.yahoo.com/quote/BRK-B",
      "price": 477.3500061035156,
      "price_fmt": "477.35",
      "change": -1.149993896484375,
      "change_fmt": "1.1500",
      "change_pct": -0.00240333102713558,
      "change_pct_fmt": "-0.24%",
      "change_arrow": "▼",
      "css": "down",
      "history": [
        "468.49",
        "474.66",
        "479.20",
        "478.50",
        "477.35"
      ],
      "history_dates": [
        "03/27",
        "03/30",
        "03/31",
        "04/01",
        "04/02"
      ],
      "change_5d": 0.018911857358378477,
      "change_5d_fmt": "+1.89%",
      "css5d": "up",
      "as_of": "04/03 05:00",
      "market_name": "NYSE/NASDAQ",
      "market_open": false,
      "name": "Berkshire Hathaway B",
      "news_titles": [],
      "analysis": "伯克希尔微跌，作为防御性标的，近期资金流向略显保守，缺乏波动空间。\n价值投资属性使其在震荡市中表现平稳，无剧烈预期。",
      "outlook": "neutral",
      "outlook_css": "neutral"
    },
    {
      "ticker": "LMT",
      "label": "Lockheed Martin",
      "url": "https://finance.yahoo.com/quote/LMT",
      "price": 622.7899780273438,
      "price_fmt": "622.79",
      "change": 5.14996337890625,
      "change_fmt": "5.1500",
      "change_pct": 0.008338131041975356,
      "change_pct_fmt": "+0.83%",
      "change_arrow": "▲",
      "css": "up",
      "history": [
        "615.84",
        "598.57",
        "604.39",
        "617.64",
        "622.79"
      ],
      "history_dates": [
        "03/27",
        "03/30",
        "03/31",
        "04/01",
        "04/02"
      ],
      "change_5d": 0.011285319025724973,
      "change_5d_fmt": "+1.13%",
      "css5d": "up",
      "as_of": "04/03 05:00",
      "market_name": "NYSE/NASDAQ",
      "market_open": false,
      "name": "Lockheed Martin",
      "news_titles": [],
      "analysis": "洛克希德马丁上涨，受地缘政治局势驱动，国防板块在当前环境下受避险资金青睐。\n全球局势不确定性加大，国防支出增长保障业绩。",
      "outlook": "bullish",
      "outlook_css": "bullish"
    },
    {
      "ticker": "7203.T",
      "label": "Toyota Motor",
      "url": "https://finance.yahoo.com/quote/7203.T",
      "price": 3259.0,
      "price_fmt": "3,259.00",
      "change": 4.0,
      "change_fmt": "4.0000",
      "change_pct": 0.001228878648233487,
      "change_pct_fmt": "+0.12%",
      "change_arrow": "▲",
      "css": "up",
      "history": [
        "3,162.00",
        "3,311.00",
        "3,262.00",
        "3,255.00",
        "3,259.00"
      ],
      "history_dates": [
        "03/31",
        "04/01",
        "04/02",
        "04/03",
        "04/06"
      ],
      "change_5d": 0.030676786843769767,
      "change_5d_fmt": "+3.07%",
      "css5d": "up",
      "as_of": "04/06 13:48",
      "market_name": "TSE",
      "market_open": true,
      "name": "Toyota Motor",
      "news_titles": [],
      "analysis": "丰田汽车保持微涨，随大盘趋势平稳，市场关注其汽车销量数据。\n具备稳健的增长基本面，受日元弱势支撑出口逻辑。",
      "outlook": "bullish",
      "outlook_css": "bullish"
    },
    {
      "ticker": "9984.T",
      "label": "SoftBank Group",
      "url": "https://finance.yahoo.com/quote/9984.T",
      "price": 3666.0,
      "price_fmt": "3,666.00",
      "change": 57.0,
      "change_fmt": "57.000",
      "change_pct": 0.015793848711554447,
      "change_pct_fmt": "+1.58%",
      "change_arrow": "▲",
      "css": "up",
      "history": [
        "3,555.00",
        "3,764.00",
        "3,604.00",
        "3,609.00",
        "3,666.00"
      ],
      "history_dates": [
        "03/31",
        "04/01",
        "04/02",
        "04/03",
        "04/06"
      ],
      "change_5d": 0.031223628691983123,
      "change_5d_fmt": "+3.12%",
      "css5d": "up",
      "as_of": "04/06 13:48",
      "market_name": "TSE",
      "market_open": true,
      "name": "SoftBank Group",
      "news_titles": [],
      "analysis": "软银集团表现亮眼，受益于旗下科技资产组合的重估，走势强于大盘。\n科技领域投资组合带来的账面价值提升预期。",
      "outlook": "bullish",
      "outlook_css": "bullish"
    },
    {
      "ticker": "INDA",
      "label": "iShares MSCI India ETF",
      "url": "https://finance.yahoo.com/quote/INDA",
      "price": 46.650001525878906,
      "price_fmt": "46.650",
      "change": -0.05999755859375,
      "change_fmt": "0.0600",
      "change_pct": -0.0012844692735970186,
      "change_pct_fmt": "-0.13%",
      "change_arrow": "▼",
      "css": "down",
      "history": [
        "45.820",
        "45.420",
        "46.840",
        "46.710",
        "46.650"
      ],
      "history_dates": [
        "03/27",
        "03/30",
        "03/31",
        "04/01",
        "04/02"
      ],
      "change_5d": 0.01811440062380541,
      "change_5d_fmt": "+1.81%",
      "css5d": "up",
      "as_of": "04/03 05:00",
      "market_name": "NYSE/NASDAQ",
      "market_open": false,
      "name": "iShares MSCI India ETF",
      "news_titles": [],
      "analysis": "印度市场ETF窄幅微跌，在经历近期上涨后进入休整期，投资者观望情绪较浓。\n长期看好印度增长潜力，当前属正常回调。",
      "outlook": "bullish",
      "outlook_css": "bullish"
    }
  ],
  "market_news": [
    {
      "title": "道琼斯期货：市场反弹之际，领涨股票表现坚挺；关注这一看涨信号",
      "article": "Dow Jones Futures: Leading Stocks Stand Tall As Market Bounces; Look For This Bullish Signal",
      "summary": "关键词：Dow Jones Futures, 股市走势, 技术信号<br>\n总结：在Dow Jones Futures市场表现走强的背景下，美股市场迎来反弹，多只领涨个股展现出较强的韧性。分析指出，投资者当前应密切关注市场盘面，积极捕捉潜在的看涨信号。随着个股分化加剧，市场整体呈现企稳回升态势，这为后续的操作提供了新的契机。专业人士建议投资者在评估风险的同时，紧盯技术指标的突破，以准确把握市场进一步向上反弹的明确买入时机。"
    },
    {
      "title": "日韩股市高开，投资者正评估Donald Trump（特朗普）关于伊朗战争的言论及延长最后期限的影响",
      "article": "In an expletive-filled social media post, Trump also vowed to bring \"Hell\" to the country after the U.S. forces had rescued an American airman shot down in Iran last week.",
      "summary": "关键词：Trump, Iran, 美国空军<br>\n总结：在近期美军成功营救一名在Iran被击落的美国飞行员后，Donald Trump（唐纳德·特朗普）在社交媒体上发表了极具争议的言论。他使用大量粗俗语言对此事进行了评价，并公然威胁称将为该国带来“地狱”般的报复。这一激进表态引发了外界对中东局势升级及Donald Trump（唐纳德·特朗普）个人言行风格的广泛关注，同时也加剧了本就紧张的美伊外交关系。"
    }
  ],
  "japan_news": [
    {
      "title": "长期利率一度升至2.41%，创下约27年以来的新高",
      "article": "週明け6日の債券市場は、イラン情勢を背景に原油の先物価格が一段と上昇する中、国内でも物価高がさらに進むのではないかという見方から長期金利が2.4％を超え、1999年以来の高い水準に上昇しています。",
      "summary": "关键词：日本长期利率,原油期货,通货膨胀<br>\n总结：受伊朗局势影响，国际原油期货价格持续上涨，引发市场对日本国内通货膨胀进一步加剧的担忧。在此背景下，投资者抛售债券导致收益率飙升，日本长期利率突破2.4%，创下自1999年以来的最高水平。这一趋势反映出地缘政治风险正通过能源价格传导至金融市场，显著加重了市场对于物价持续攀升的压力，并对日本的利率环境产生了深刻影响。"
    },
    {
      "title": "股价上涨，上午收盘价较上周末上涨878.15日元",
      "article": "株価 値上がり 午前の終値 先週末比878円15銭高",
      "summary": "关键词：日经平均指数,股价,收盘<br>\n总结：日本股市在今日上午交易时段表现强劲，日经平均指数呈现大幅上涨态势。截至上午收盘，该指数较上周末收盘价上涨878.15日元。此次价格攀升主要受到市场买盘活跃及投资者情绪回暖的推动，展现出较为积极的短期行情走势，反映了目前市场资金对于相关板块的看好，整体交易环境较为乐观。"
    }
  ],
  "hot_markets": [
    {
      "country": "South Korea",
      "label": "South Korea",
      "etf": "EWY",
      "etf_source": "iShares MSCI South Korea",
      "pct": -0.02654094788244712,
      "url": "https://finance.yahoo.com/quote/EWY",
      "price_fmt": "122.87",
      "change_pct_fmt": "-2.65%",
      "constituents_source": "iShares EWY top holdings",
      "top_movers": [
        {
          "ticker": "051910.KS",
          "price": 317500.0,
          "price_fmt": "317,500",
          "pct": 0.042692939244663386,
          "change_pct_fmt": "+4.27%",
          "change_arrow": "▲",
          "css": "up",
          "url": "https://finance.yahoo.com/quote/051910.KS",
          "name": "LGCHEM"
        },
        {
          "ticker": "005930.KS",
          "price": 191700.0,
          "price_fmt": "191,700",
          "pct": 0.02953813104189044,
          "change_pct_fmt": "+2.95%",
          "change_arrow": "▲",
          "css": "up",
          "url": "https://finance.yahoo.com/quote/005930.KS",
          "name": "SamsungElec"
        },
        {
          "ticker": "006400.KS",
          "price": 450500.0,
          "price_fmt": "450,500",
          "pct": 0.027366020524515394,
          "change_pct_fmt": "+2.74%",
          "change_arrow": "▲",
          "css": "up",
          "url": "https://finance.yahoo.com/quote/006400.KS",
          "name": "SAMSUNG SDI CO.,LTD."
        }
      ],
      "ticker": "EWY",
      "name": "South Korea",
      "news_titles": [
        "051910.KS +4.27%",
        "005930.KS +2.95%",
        "006400.KS +2.74%"
      ],
      "analysis": "韩股ETF大跌，尽管个股表现亮眼，但整体市场结构面临剧烈波动挑战。\n外资撤离压力明显，短期波动率风险上升。",
      "outlook": "bearish",
      "outlook_css": "bearish",
      "news": []
    }
  ],
  "portfolio": {
    "base_currency": "JPY",
    "positions": [
      {
        "ticker": "NVDA",
        "name": "NVIDIA",
        "strategy": "speculative",
        "account": "SBI証券",
        "cost_ccy": "USD",
        "needs_fx": true,
        "total_shares": 50,
        "avg_cost": 102.0,
        "avg_cost_fmt": "102.00",
        "current_price": 177.38999938964844,
        "price_fmt": "177.39",
        "day_change_pct": 0.009331433227018137,
        "day_change_fmt": "+0.93%",
        "day_css": "up",
        "price_effect": 0.009331433227018137,
        "price_effect_fmt": "+0.93%",
        "price_effect_css": "up",
        "fx_effect": 0.0003574298041732417,
        "fx_effect_fmt": "+0.04%",
        "fx_effect_css": "up",
        "total_base_return": 0.009692198363542515,
        "total_base_return_fmt": "+0.97%",
        "total_base_return_css": "up",
        "pnl_pct": 0.7391176410749847,
        "pnl_pct_fmt": "+73.91%",
        "pnl_css": "up",
        "value_base": 1415111.017942871,
        "pnl_base": 601416.1967758788,
        "prev_value_base": 1401527.1389007566,
        "lots": [
          {
            "shares": 20,
            "cost": 90.0,
            "cost_fmt": "90.000",
            "date": "2024-01-15",
            "pnl_pct": 0.970999993218316,
            "pnl_pct_fmt": "+97.10%",
            "pnl_css": "up"
          },
          {
            "shares": 30,
            "cost": 110.0,
            "cost_fmt": "110.00",
            "date": "2024-03-20",
            "pnl_pct": 0.6126363580877131,
            "pnl_pct_fmt": "+61.26%",
            "pnl_css": "up"
          }
        ],
        "action": "hold",
        "advice": "AI需求依旧强劲，整体仓位已重，建议继续持有观察业绩，暂不宜追高加仓，等待回撤机会。",
        "weight": 0.32764697502012474,
        "weight_fmt": "32.8%",
        "error": false
      },
      {
        "ticker": "7203.T",
        "name": "Toyota Motor",
        "strategy": "dca",
        "account": "NISA",
        "cost_ccy": "JPY",
        "needs_fx": false,
        "total_shares": 30,
        "avg_cost": 2716.6666666666665,
        "avg_cost_fmt": "2,716.67",
        "current_price": 3259.0,
        "price_fmt": "3,259.00",
        "day_change_pct": 0.001228878648233487,
        "day_change_fmt": "+0.12%",
        "day_css": "up",
        "price_effect": 0.001228878648233487,
        "price_effect_fmt": "+0.12%",
        "price_effect_css": "up",
        "fx_effect": 0.0,
        "fx_effect_fmt": "-",
        "fx_effect_css": "flat",
        "total_base_return": 0.001228878648233487,
        "total_base_return_fmt": "+0.12%",
        "total_base_return_css": "up",
        "pnl_pct": 0.1996319018404908,
        "pnl_pct_fmt": "+19.96%",
        "pnl_css": "up",
        "value_base": 97770.0,
        "pnl_base": 16270.0,
        "prev_value_base": 97650.0,
        "lots": [
          {
            "shares": 10,
            "cost": 2600,
            "cost_fmt": "2,600.00",
            "date": "2024-01-05",
            "pnl_pct": 0.25346153846153846,
            "pnl_pct_fmt": "+25.35%",
            "pnl_css": "up"
          },
          {
            "shares": 10,
            "cost": 2750,
            "cost_fmt": "2,750.00",
            "date": "2024-02-05",
            "pnl_pct": 0.18509090909090908,
            "pnl_pct_fmt": "+18.51%",
            "pnl_css": "up"
          },
          {
            "shares": 10,
            "cost": 2800,
            "cost_fmt": "2,800.00",
            "date": "2024-03-05",
            "pnl_pct": 0.16392857142857142,
            "pnl_pct_fmt": "+16.39%",
            "pnl_css": "up"
          }
        ],
        "action": "add",
        "advice": "作为日本核心制造业，长期基本面稳健且估值合理。利用NISA额度持续定投有利于摊平成本，获取长期分红。",
        "weight": 0.022637124820273878,
        "weight_fmt": "2.3%",
        "error": false
      },
      {
        "ticker": "IAU",
        "name": "iShares Gold Trust",
        "strategy": "dca",
        "account": "SBI証券",
        "cost_ccy": "USD",
        "needs_fx": true,
        "total_shares": 200,
        "avg_cost": 45.5,
        "avg_cost_fmt": "45.500",
        "current_price": 87.94000244140625,
        "price_fmt": "87.940",
        "day_change_pct": -0.019402295471101925,
        "day_change_fmt": "-1.94%",
        "day_css": "down",
        "price_effect": -0.019402295471101925,
        "price_effect_fmt": "-1.94%",
        "price_effect_css": "down",
        "fx_effect": 0.0003574298041732417,
        "fx_effect_fmt": "+0.04%",
        "fx_effect_css": "up",
        "total_base_return": -0.019051800625599413,
        "total_base_return_fmt": "-1.91%",
        "total_base_return_css": "down",
        "pnl_pct": 0.932747306404533,
        "pnl_pct_fmt": "+93.27%",
        "pnl_css": "up",
        "value_base": 2806130.374901369,
        "pnl_base": 1354243.5371328145,
        "prev_value_base": 2860630.537566589,
        "lots": [
          {
            "shares": 200,
            "cost": 45.5,
            "cost_fmt": "45.500",
            "date": "2024-06-01",
            "pnl_pct": 0.932747306404533,
            "pnl_pct_fmt": "+93.27%",
            "pnl_css": "up"
          }
        ],
        "action": "hold",
        "advice": "持仓占比高达65%，组合风险过于集中。虽长期看好黄金抗通胀，但当前无需加仓，应保持持有并关注资产均衡。",
        "weight": 0.6497159001596013,
        "weight_fmt": "65.0%",
        "error": false
      }
    ],
    "benchmark_tickers": [
      "^GSPC",
      "^N225"
    ],
    "day_return": -0.009357358546641707,
    "day_return_fmt": "-0.94%",
    "day_return_css": "down",
    "total_value": 4319011.39284424,
    "total_value_fmt": "4,319,011",
    "total_cost": 2347081.658935547,
    "total_pnl": 1971929.7339086933,
    "total_pnl_fmt": "+1,971,930",
    "total_pnl_pct": 0.8401623890678804,
    "total_pnl_pct_fmt": "+84.02%",
    "total_css": "up",
    "fx_rates": {
      "USD": {
        "rate": 159.54800415039062,
        "prev_rate": 159.49099731445312,
        "day_change": 0.0003574298041732417,
        "rate_fmt": "159.55",
        "day_change_fmt": "+0.04%",
        "css": "up"
      }
    },
    "benchmarks": [
      {
        "label": "S&P 500",
        "ticker": "^GSPC",
        "return": 0.0011208758485562616,
        "return_fmt": "+0.11%",
        "alpha": -0.01047823439519797,
        "alpha_fmt": "-1.05%",
        "alpha_css": "down"
      },
      {
        "label": "Nikkei 225",
        "ticker": "^N225",
        "return": 0.012177478873847366,
        "return_fmt": "+1.22%",
        "alpha": -0.021534837420489075,
        "alpha_fmt": "-2.15%",
        "alpha_css": "down"
      }
    ],
    "risk_alerts": [
      {
        "ticker": "7203.T",
        "name": "Toyota Motor",
        "alert": "日韩股市波动及汇率风险可能影响丰田股价表现。"
      }
    ]
  }
}